ShuziJulian/README.md
ShuziJulian/__init__.py
ShuziJulian/__main__.py
ShuziJulian/file.epub
ShuziJulian/index.html
ShuziJulian/css/__init__.py
ShuziJulian/css/annotations.css
ShuziJulian/css/main.css
ShuziJulian/css/normalize.css
ShuziJulian/css/popup.css
ShuziJulian/font/__init__.py
ShuziJulian/font/fontello.eot
ShuziJulian/font/fontello.svg
ShuziJulian/font/fontello.ttf
ShuziJulian/font/fontello.woff
ShuziJulian/img/__init__.py
ShuziJulian/img/annotator-glyph-sprite.png
ShuziJulian/img/annotator-icon-sprite.png
ShuziJulian/img/apple-touch-icon.png
ShuziJulian/img/cancelfullscreen.png
ShuziJulian/img/close.png
ShuziJulian/img/fullscreen.png
ShuziJulian/img/loader.gif
ShuziJulian/img/menu-icon.png
ShuziJulian/img/save.png
ShuziJulian/img/saved.png
ShuziJulian/img/settings-s.png
ShuziJulian/img/settings.png
ShuziJulian/img/star.png
ShuziJulian/js/__init__.py
ShuziJulian/js/epub.js
ShuziJulian/js/epub.min.js
ShuziJulian/js/epub.min.map
ShuziJulian/js/hooks.min.js
ShuziJulian/js/hooks.min.map
ShuziJulian/js/reader.js
ShuziJulian/js/reader.js.map
ShuziJulian/js/reader.min.js
ShuziJulian/js/reader.min.map
ShuziJulian/js/hooks/__init__.py
ShuziJulian/js/hooks/extensions/__init__.py
ShuziJulian/js/hooks/extensions/highlight.js
ShuziJulian/js/libs/__init__.py
ShuziJulian/js/libs/jquery.min.js
ShuziJulian/js/libs/localforage.min.js
ShuziJulian/js/libs/screenfull.js
ShuziJulian/js/libs/screenfull.min.js
ShuziJulian/js/libs/zip.min.js
ShuziJulian/js/plugins/__init__.py
ShuziJulian/js/plugins/hypothesis.js
ShuziJulian/js/plugins/search.js
shuzi_julian-2024.3.3.0.dist-info/METADATA
shuzi_julian-2024.3.3.0.dist-info/WHEEL
shuzi_julian-2024.3.3.0.dist-info/entry_points.txt
shuzi_julian-2024.3.3.0.dist-info/top_level.txt
shuzi_julian-2024.3.3.0.dist-info/RECORD
